{"0": {"traffic_light_0": {"coords": [126, 373, 140, 397], "state": "red", "affect": true}}, "1": {}, "2": {"traffic_light_0": {"coords": [590, 229, 598, 249], "state": "green", "affect": true}}, "3": {"traffic_light_0": {"coords": [590, 229, 598, 249], "state": "green", "affect": true}}, "4": {"traffic_light_0": {"coords": [590, 229, 598, 249], "state": "green", "affect": true}}, "5": {"traffic_light_0": {"coords": [590, 228, 598, 248], "state": "green", "affect": true}}, "6": {"traffic_light_0": {"coords": [590, 227, 598, 248], "state": "green", "affect": true}}, "7": {"traffic_light_0": {"coords": [590, 226, 600, 248], "state": "green", "affect": true}, "traffic_light_1": {"coords": [590, 224, 606, 253], "state": "green", "affect": true}}, "8": {"traffic_light_0": {"coords": [590, 226, 598, 248], "state": "green", "affect": true}}, "9": {"traffic_light_0": {"coords": [590, 227, 598, 248], "state": "green", "affect": true}}, "10": {"traffic_light_0": {"coords": [591, 227, 599, 248], "state": "green", "affect": true}}, "11": {"traffic_light_0": {"coords": [590, 227, 599, 248], "state": "green", "affect": true}}, "12": {"traffic_light_0": {"coords": [591, 225, 600, 247], "state": "green", "affect": true}, "traffic_light_1": {"coords": [591, 223, 607, 252], "state": "green", "affect": true}}, "13": {"traffic_light_0": {"coords": [590, 224, 600, 246], "state": "green", "affect": true}, "traffic_light_1": {"coords": [590, 222, 606, 251], "state": "green", "affect": true}}, "14": {"traffic_light_0": {"coords": [591, 225, 600, 246], "state": "green", "affect": true}, "traffic_light_1": {"coords": [590, 222, 606, 251], "state": "green", "affect": true}}, "15": {"traffic_light_0": {"coords": [590, 220, 600, 244], "state": "green", "affect": true}}, "16": {"traffic_light_0": {"coords": [590, 217, 602, 245], "state": "green", "affect": true}, "traffic_light_1": {"coords": [588, 217, 598, 239], "state": "green", "affect": true}}, "17": {"traffic_light_0": {"coords": [591, 217, 602, 244], "state": "green", "affect": true}, "traffic_light_1": {"coords": [588, 217, 598, 238], "state": "green", "affect": true}}, "18": {"traffic_light_0": {"coords": [591, 216, 601, 239], "state": "green", "affect": true}}, "19": {"traffic_light_0": {"coords": [591, 213, 601, 235], "state": "green", "affect": true}}, "20": {"traffic_light_0": {"coords": [590, 210, 601, 233], "state": "green", "affect": true}}, "21": {"traffic_light_0": {"coords": [591, 210, 601, 233], "state": "green", "affect": true}}, "22": {"traffic_light_0": {"coords": [591, 208, 603, 230], "state": "green", "affect": true}}, "23": {"traffic_light_0": {"coords": [590, 207, 602, 229], "state": "green", "affect": true}}, "24": {"traffic_light_0": {"coords": [591, 206, 602, 228], "state": "green", "affect": true}}, "25": {"traffic_light_0": {"coords": [592, 205, 603, 228], "state": "green", "affect": true}}, "26": {"traffic_light_0": {"coords": [591, 201, 602, 226], "state": "green", "affect": true}}, "27": {"traffic_light_0": {"coords": [590, 200, 602, 225], "state": "green", "affect": true}}, "28": {"traffic_light_0": {"coords": [592, 201, 602, 222], "state": "green", "affect": true}}, "29": {"traffic_light_0": {"coords": [593, 202, 602, 222], "state": "green", "affect": true}}, "30": {"traffic_light_0": {"coords": [592, 199, 603, 224], "state": "green", "affect": true}}, "31": {}, "32": {"traffic_light_0": {"coords": [593, 193, 604, 219], "state": "green", "affect": true}}, "33": {"traffic_light_0": {"coords": [592, 192, 602, 217], "state": "green", "affect": true}}, "34": {"traffic_light_0": {"coords": [593, 191, 604, 216], "state": "green", "affect": true}}, "35": {"traffic_light_0": {"coords": [594, 185, 605, 211], "state": "green", "affect": true}}, "36": {"traffic_light_0": {"coords": [594, 184, 608, 213], "state": "green", "affect": true}, "traffic_light_1": {"coords": [594, 183, 603, 206], "state": "green", "affect": true}}, "37": {"traffic_light_0": {"coords": [594, 178, 609, 210], "state": "green", "affect": true}}, "38": {"traffic_light_0": {"coords": [595, 176, 608, 206], "state": "green", "affect": true}}, "39": {"traffic_light_0": {"coords": [595, 176, 609, 206], "state": "green", "affect": true}}, "40": {"traffic_light_0": {"coords": [596, 174, 608, 203], "state": "green", "affect": true}}, "41": {"traffic_light_0": {"coords": [596, 168, 608, 199], "state": "green", "affect": true}}, "42": {"traffic_light_0": {"coords": [595, 160, 611, 196], "state": "green", "affect": true}}, "43": {"traffic_light_0": {"coords": [595, 160, 611, 195], "state": "green", "affect": true}}, "44": {"traffic_light_0": {"coords": [596, 161, 609, 193], "state": "green", "affect": true}}, "45": {"traffic_light_0": {"coords": [595, 159, 609, 193], "state": "green", "affect": true}}, "46": {"traffic_light_0": {"coords": [596, 158, 611, 192], "state": "green", "affect": true}}, "47": {"traffic_light_0": {"coords": [597, 159, 608, 185], "state": "green", "affect": true}}, "48": {"traffic_light_0": {"coords": [596, 157, 610, 185], "state": "green", "affect": true}}, "49": {"traffic_light_0": {"coords": [597, 151, 611, 179], "state": "green", "affect": true}}, "50": {"traffic_light_0": {"coords": [597, 145, 614, 180], "state": "green", "affect": true}}, "51": {"traffic_light_0": {"coords": [600, 141, 613, 173], "state": "green", "affect": true}}, "52": {"traffic_light_0": {"coords": [600, 137, 616, 171], "state": "green", "affect": true}}, "53": {"traffic_light_0": {"coords": [600, 126, 619, 167], "state": "green", "affect": true}}, "54": {"traffic_light_0": {"coords": [601, 125, 619, 164], "state": "green", "affect": true}}, "55": {"traffic_light_0": {"coords": [601, 124, 618, 161], "state": "green", "affect": true}}, "56": {"traffic_light_0": {"coords": [602, 121, 620, 159], "state": "green", "affect": true}}, "57": {"traffic_light_0": {"coords": [602, 115, 619, 153], "state": "green", "affect": true}}, "58": {"traffic_light_0": {"coords": [603, 114, 619, 153], "state": "green", "affect": true}}, "59": {"traffic_light_0": {"coords": [604, 115, 619, 146], "state": "green", "affect": true}}, "60": {"traffic_light_0": {"coords": [918, 90, 947, 157], "state": "green", "affect": true}, "traffic_light_1": {"coords": [603, 102, 620, 138], "state": "green", "affect": true}}, "61": {"traffic_light_0": {"coords": [934, 91, 959, 153], "state": "green", "affect": true}}, "62": {"traffic_light_0": {"coords": [943, 90, 966, 147], "state": "green", "affect": true}, "traffic_light_1": {"coords": [604, 97, 618, 126], "state": "green", "affect": true}}, "63": {"traffic_light_0": {"coords": [606, 88, 625, 128], "state": "green", "affect": true}, "traffic_light_1": {"coords": [957, 82, 982, 141], "state": "green", "affect": true}}, "64": {"traffic_light_0": {"coords": [967, 79, 991, 135], "state": "green", "affect": true}, "traffic_light_1": {"coords": [607, 76, 629, 121], "state": "green", "affect": true}}, "65": {"traffic_light_0": {"coords": [608, 75, 629, 118], "state": "green", "affect": true}, "traffic_light_1": {"coords": [611, 83, 624, 115], "state": "green", "affect": true}, "traffic_light_2": {"coords": [973, 78, 1001, 132], "state": "green", "affect": true}}, "66": {"traffic_light_0": {"coords": [609, 69, 629, 112], "state": "green", "affect": true}, "traffic_light_1": {"coords": [986, 57, 1012, 128], "state": "green", "affect": true}}, "67": {"traffic_light_0": {"coords": [609, 60, 630, 107], "state": "green", "affect": true}, "traffic_light_1": {"coords": [995, 51, 1027, 122], "state": "green", "affect": true}}, "68": {"traffic_light_0": {"coords": [611, 58, 630, 100], "state": "green", "affect": true}}, "69": {"traffic_light_0": {"coords": [612, 51, 640, 97], "state": "green", "affect": true}, "traffic_light_1": {"coords": [1016, 37, 1051, 114], "state": "green", "affect": true}}, "70": {"traffic_light_0": {"coords": [613, 39, 636, 93], "state": "green", "affect": true}, "traffic_light_1": {"coords": [1031, 32, 1065, 108], "state": "green", "affect": true}}, "71": {"traffic_light_0": {"coords": [615, 28, 639, 86], "state": "green", "affect": true}, "traffic_light_1": {"coords": [1047, 18, 1082, 97], "state": "green", "affect": true}}, "72": {"traffic_light_0": {"coords": [615, 18, 641, 80], "state": "green", "affect": true}, "traffic_light_1": {"coords": [1062, 15, 1097, 91], "state": "green", "affect": true}}, "73": {"traffic_light_0": {"coords": [616, 19, 644, 70], "state": "green", "affect": true}, "traffic_light_1": {"coords": [1079, 4, 1112, 80], "state": "green", "affect": true}}, "74": {"traffic_light_0": {"coords": [617, 9, 645, 63], "state": "green", "affect": true}}, "75": {"traffic_light_0": {"coords": [620, 5, 644, 51], "state": "green", "affect": true}}, "76": {}, "77": {}, "78": {}, "79": {}, "80": {}, "81": {}, "82": {}, "83": {}, "84": {}, "85": {}, "86": {}, "87": {}, "88": {}, "89": {}, "90": {}, "91": {}, "92": {}, "93": {}, "94": {}, "95": {}, "96": {}, "97": {}, "98": {}, "99": {}, "100": {}, "101": {}, "102": {}, "103": {}, "104": {}, "105": {}, "106": {}, "107": {}, "108": {}, "109": {}, "110": {}, "111": {}, "112": {}, "113": {}, "114": {}, "115": {}, "116": {}, "117": {}, "118": {}, "119": {}, "120": {}, "121": {}, "122": {}, "123": {}, "124": {}, "125": {}, "126": {}, "127": {}, "128": {}, "129": {}, "130": {}, "131": {}, "132": {}, "133": {}, "134": {}, "135": {}, "136": {}, "137": {}, "138": {}, "139": {}, "140": {}, "141": {}, "142": {}, "143": {}, "144": {}, "145": {}, "146": {}, "147": {}, "148": {}, "149": {}, "150": {}, "151": {}, "152": {}, "153": {}, "154": {}, "155": {"traffic_light_0": {"coords": [170, 358, 181, 377], "state": "red", "affect": true}}, "156": {}, "157": {}, "158": {}, "159": {}, "160": {}, "161": {}, "162": {}, "163": {}, "164": {}, "165": {}, "166": {}, "167": {}, "168": {}, "169": {}, "170": {}, "171": {}, "172": {}, "173": {}, "174": {}, "175": {}, "176": {}, "177": {}, "178": {}, "179": {}, "180": {}, "181": {}, "182": {}, "183": {}, "184": {}, "185": {}, "186": {}, "187": {}, "188": {}, "189": {}, "190": {"traffic_light_0": {"coords": [554, 229, 564, 252], "state": "green", "affect": true}}, "191": {}, "192": {}, "193": {}, "194": {"traffic_light_0": {"coords": [688, 244, 698, 265], "state": "green", "affect": true}}, "195": {}, "196": {"traffic_light_0": {"coords": [552, 220, 564, 248], "state": "green", "affect": true}, "traffic_light_1": {"coords": [690, 243, 698, 263], "state": "green", "affect": true}}, "197": {"traffic_light_0": {"coords": [552, 220, 563, 247], "state": "green", "affect": true}}, "198": {"traffic_light_0": {"coords": [552, 219, 563, 247], "state": "green", "affect": true}, "traffic_light_1": {"coords": [690, 242, 699, 264], "state": "green", "affect": true}}, "199": {"traffic_light_0": {"coords": [554, 219, 565, 246], "state": "green", "affect": true}, "traffic_light_1": {"coords": [690, 239, 699, 260], "state": "green", "affect": true}, "traffic_light_2": {"coords": [552, 219, 561, 242], "state": "green", "affect": true}}, "200": {"traffic_light_0": {"coords": [554, 219, 565, 246], "state": "green", "affect": true}, "traffic_light_1": {"coords": [552, 219, 561, 242], "state": "green", "affect": true}}, "201": {}, "202": {}, "203": {"traffic_light_0": {"coords": [551, 212, 563, 239], "state": "green", "affect": true}}, "204": {}, "205": {}, "206": {}, "207": {}, "208": {}, "209": {}, "210": {}, "211": {}, "212": {}, "213": {}, "214": {}, "215": {}, "216": {}, "217": {"traffic_light_0": {"coords": [542, 191, 555, 219], "state": "green", "affect": true}}, "218": {"traffic_light_0": {"coords": [543, 191, 555, 217], "state": "green", "affect": true}}, "219": {"traffic_light_0": {"coords": [543, 191, 555, 217], "state": "green", "affect": true}}, "220": {"traffic_light_0": {"coords": [713, 219, 723, 245], "state": "green", "affect": true}}, "221": {}, "222": {}, "223": {}, "224": {}, "225": {"traffic_light_0": {"coords": [720, 210, 732, 235], "state": "green", "affect": true}}, "226": {}, "227": {}, "228": {}, "229": {}, "230": {"traffic_light_0": {"coords": [534, 173, 547, 200], "state": "green", "affect": true}}, "231": {}, "232": {"traffic_light_0": {"coords": [533, 161, 548, 197], "state": "green", "affect": true}}, "233": {"traffic_light_0": {"coords": [534, 159, 548, 195], "state": "green", "affect": true}}, "234": {"traffic_light_0": {"coords": [533, 158, 548, 195], "state": "green", "affect": true}}, "235": {"traffic_light_0": {"coords": [532, 156, 548, 192], "state": "green", "affect": true}}, "236": {"traffic_light_0": {"coords": [531, 157, 544, 190], "state": "green", "affect": true}, "traffic_light_1": {"coords": [744, 204, 753, 224], "state": "green", "affect": true}}, "237": {"traffic_light_0": {"coords": [532, 155, 544, 188], "state": "green", "affect": true}, "traffic_light_1": {"coords": [745, 198, 754, 222], "state": "green", "affect": true}}, "238": {}, "239": {"traffic_light_0": {"coords": [532, 143, 549, 181], "state": "green", "affect": true}, "traffic_light_1": {"coords": [751, 191, 762, 217], "state": "green", "affect": true}}, "240": {}, "241": {}, "242": {"traffic_light_0": {"coords": [758, 183, 770, 209], "state": "green", "affect": true}}, "243": {}, "244": {}, "245": {}, "246": {"traffic_light_0": {"coords": [530, 124, 545, 162], "state": "green", "affect": true}}, "247": {"traffic_light_0": {"coords": [527, 124, 541, 160], "state": "green", "affect": true}}, "248": {"traffic_light_0": {"coords": [528, 124, 544, 159], "state": "green", "affect": true}}, "249": {"traffic_light_0": {"coords": [528, 125, 542, 156], "state": "green", "affect": true}}, "250": {"traffic_light_0": {"coords": [528, 119, 543, 154], "state": "green", "affect": true}}, "251": {"traffic_light_0": {"coords": [525, 109, 544, 153], "state": "green", "affect": true}}, "252": {"traffic_light_0": {"coords": [526, 107, 543, 149], "state": "green", "affect": true}}, "253": {}, "254": {"traffic_light_0": {"coords": [801, 160, 815, 191], "state": "green", "affect": true}}, "255": {"traffic_light_0": {"coords": [525, 90, 544, 134], "state": "green", "affect": true}, "traffic_light_1": {"coords": [806, 165, 816, 189], "state": "green", "affect": true}}, "256": {"traffic_light_0": {"coords": [811, 159, 822, 186], "state": "green", "affect": true}, "traffic_light_1": {"coords": [525, 89, 544, 130], "state": "green", "affect": true}}, "257": {}, "258": {"traffic_light_0": {"coords": [520, 62, 548, 123], "state": "green", "affect": true}}, "259": {}, "260": {}, "261": {}, "262": {}, "263": {}, "264": {}, "265": {}, "266": {}, "267": {}, "268": {}, "269": {}, "270": {}, "271": {}, "272": {}, "273": {}, "274": {}, "275": {}, "276": {}, "277": {}, "278": {}, "279": {}, "280": {}, "281": {}, "282": {}, "283": {}, "284": {}, "285": {}, "286": {}, "287": {}, "288": {}, "289": {}, "290": {}, "291": {}, "292": {}, "293": {}, "294": {}, "295": {}, "296": {"traffic_light_0": {"coords": [901, 260, 912, 284], "state": "green", "affect": true}}, "297": {}, "298": {}, "299": {}, "300": {"traffic_light_0": {"coords": [906, 252, 916, 277], "state": "green", "affect": true}}, "301": {"traffic_light_0": {"coords": [906, 254, 916, 276], "state": "green", "affect": true}}, "302": {"traffic_light_0": {"coords": [911, 256, 921, 277], "state": "green", "affect": true}}, "303": {"traffic_light_0": {"coords": [908, 252, 918, 275], "state": "green", "affect": true}}, "304": {"traffic_light_0": {"coords": [911, 250, 922, 274], "state": "green", "affect": true}}, "305": {"traffic_light_0": {"coords": [912, 247, 922, 270], "state": "green", "affect": true}}, "306": {}, "307": {"traffic_light_0": {"coords": [913, 248, 923, 272], "state": "green", "affect": true}}, "308": {}, "309": {}, "310": {}, "311": {}, "312": {}, "313": {}, "314": {}, "315": {}, "316": {"traffic_light_0": {"coords": [936, 249, 950, 280], "state": "green", "affect": true}}, "317": {}, "318": {}, "319": {}, "320": {}, "321": {"traffic_light_0": {"coords": [944, 253, 955, 278], "state": "green", "affect": true}}, "322": {"traffic_light_0": {"coords": [944, 255, 953, 274], "state": "green", "affect": true}}, "323": {"traffic_light_0": {"coords": [945, 255, 955, 275], "state": "green", "affect": true}}, "324": {"traffic_light_0": {"coords": [948, 254, 959, 276], "state": "green", "affect": true}}, "325": {"traffic_light_0": {"coords": [952, 253, 963, 276], "state": "green", "affect": true}}, "326": {"traffic_light_0": {"coords": [950, 253, 962, 277], "state": "green", "affect": true}}, "327": {}, "328": {}, "329": {}, "330": {}, "331": {}, "332": {}, "333": {}, "334": {}, "335": {}, "336": {}, "337": {}, "338": {}, "339": {}, "340": {}, "341": {}, "342": {"traffic_light_0": {"coords": [966, 253, 975, 275], "state": "green", "affect": true}}, "343": {"traffic_light_0": {"coords": [974, 253, 985, 277], "state": "green", "affect": true}}, "344": {"traffic_light_0": {"coords": [975, 255, 986, 279], "state": "green", "affect": true}}, "345": {"traffic_light_0": {"coords": [975, 256, 986, 279], "state": "green", "affect": true}}, "346": {"traffic_light_0": {"coords": [976, 257, 987, 281], "state": "green", "affect": true}}, "347": {}, "348": {}, "349": {"traffic_light_0": {"coords": [868, 316, 875, 332], "state": "green", "affect": true}}, "350": {"traffic_light_0": {"coords": [868, 316, 876, 331], "state": "green", "affect": true}}, "351": {"traffic_light_0": {"coords": [584, 264, 592, 282], "state": "green", "affect": true}, "traffic_light_1": {"coords": [871, 313, 879, 331], "state": "green", "affect": true}}, "352": {"traffic_light_0": {"coords": [873, 313, 883, 333], "state": "green", "affect": true}}, "353": {"traffic_light_0": {"coords": [875, 314, 883, 332], "state": "green", "affect": true}}, "354": {"traffic_light_0": {"coords": [584, 262, 592, 279], "state": "green", "affect": true}, "traffic_light_1": {"coords": [876, 312, 885, 331], "state": "green", "affect": true}}, "355": {"traffic_light_0": {"coords": [878, 310, 888, 330], "state": "green", "affect": true}, "traffic_light_1": {"coords": [690, 263, 700, 284], "state": "green", "affect": true}, "traffic_light_2": {"coords": [584, 262, 592, 279], "state": "green", "affect": true}, "traffic_light_3": {"coords": [878, 309, 885, 325], "state": "green", "affect": true}}, "356": {"traffic_light_0": {"coords": [584, 261, 592, 279], "state": "green", "affect": true}, "traffic_light_1": {"coords": [881, 310, 889, 325], "state": "green", "affect": true}, "traffic_light_2": {"coords": [691, 262, 700, 283], "state": "green", "affect": true}, "traffic_light_3": {"coords": [879, 309, 885, 323], "state": "green", "affect": true}}, "357": {"traffic_light_0": {"coords": [691, 261, 700, 282], "state": "green", "affect": true}, "traffic_light_1": {"coords": [584, 261, 592, 278], "state": "green", "affect": true}, "traffic_light_2": {"coords": [883, 308, 890, 323], "state": "green", "affect": true}, "traffic_light_3": {"coords": [1023, 249, 1032, 269], "state": "green", "affect": true}}, "358": {"traffic_light_0": {"coords": [1023, 248, 1033, 269], "state": "green", "affect": true}, "traffic_light_1": {"coords": [891, 307, 900, 327], "state": "green", "affect": true}, "traffic_light_2": {"coords": [584, 260, 592, 277], "state": "green", "affect": true}, "traffic_light_3": {"coords": [692, 263, 701, 283], "state": "green", "affect": true}}, "359": {"traffic_light_0": {"coords": [892, 309, 901, 327], "state": "green", "affect": true}}, "360": {}, "361": {"traffic_light_0": {"coords": [696, 263, 705, 282], "state": "green", "affect": true}}, "362": {"traffic_light_0": {"coords": [698, 262, 706, 281], "state": "green", "affect": true}, "traffic_light_1": {"coords": [898, 310, 906, 328], "state": "green", "affect": true}, "traffic_light_2": {"coords": [585, 256, 593, 275], "state": "green", "affect": true}}, "363": {}, "364": {"traffic_light_0": {"coords": [1040, 247, 1052, 269], "state": "green", "affect": true}}, "365": {}, "366": {}, "367": {"traffic_light_0": {"coords": [1035, 247, 1047, 269], "state": "green", "affect": true}}, "368": {"traffic_light_0": {"coords": [706, 259, 714, 279], "state": "green", "affect": true}}, "369": {"traffic_light_0": {"coords": [706, 260, 714, 279], "state": "green", "affect": true}}, "370": {"traffic_light_0": {"coords": [707, 258, 716, 278], "state": "green", "affect": true}}, "371": {}, "372": {"traffic_light_0": {"coords": [591, 249, 599, 268], "state": "green", "affect": true}}, "373": {"traffic_light_0": {"coords": [1157, 224, 1171, 253], "state": "green", "affect": true}, "traffic_light_1": {"coords": [591, 248, 600, 268], "state": "green", "affect": true}}, "374": {"traffic_light_0": {"coords": [1158, 221, 1176, 258], "state": "green", "affect": true}, "traffic_light_1": {"coords": [591, 248, 599, 268], "state": "green", "affect": true}, "traffic_light_2": {"coords": [1162, 229, 1179, 264], "state": "green", "affect": true}}, "375": {"traffic_light_0": {"coords": [1163, 224, 1179, 256], "state": "green", "affect": true}, "traffic_light_1": {"coords": [591, 248, 600, 269], "state": "green", "affect": true}}, "376": {"traffic_light_0": {"coords": [1170, 226, 1185, 257], "state": "green", "affect": true}, "traffic_light_1": {"coords": [592, 248, 600, 269], "state": "green", "affect": true}, "traffic_light_2": {"coords": [1088, 237, 1098, 257], "state": "green", "affect": true}}, "377": {"traffic_light_0": {"coords": [592, 249, 600, 269], "state": "green", "affect": true}, "traffic_light_1": {"coords": [1169, 222, 1194, 267], "state": "green", "affect": true}}, "378": {"traffic_light_0": {"coords": [592, 248, 600, 268], "state": "green", "affect": true}, "traffic_light_1": {"coords": [1172, 221, 1193, 262], "state": "green", "affect": true}}, "379": {"traffic_light_0": {"coords": [1176, 221, 1198, 262], "state": "green", "affect": true}, "traffic_light_1": {"coords": [592, 249, 601, 269], "state": "green", "affect": true}}, "380": {"traffic_light_0": {"coords": [1180, 221, 1199, 261], "state": "green", "affect": true}, "traffic_light_1": {"coords": [592, 249, 601, 270], "state": "green", "affect": true}, "traffic_light_2": {"coords": [721, 257, 730, 278], "state": "green", "affect": true}}, "381": {"traffic_light_0": {"coords": [1184, 222, 1204, 263], "state": "green", "affect": true}, "traffic_light_1": {"coords": [721, 255, 730, 277], "state": "green", "affect": true}, "traffic_light_2": {"coords": [592, 250, 601, 271], "state": "green", "affect": true}}, "382": {"traffic_light_0": {"coords": [1190, 223, 1210, 264], "state": "green", "affect": true}, "traffic_light_1": {"coords": [722, 255, 731, 276], "state": "green", "affect": true}, "traffic_light_2": {"coords": [592, 249, 600, 268], "state": "green", "affect": true}}, "383": {"traffic_light_0": {"coords": [1197, 223, 1216, 259], "state": "green", "affect": true}}, "384": {"traffic_light_0": {"coords": [1201, 223, 1218, 259], "state": "green", "affect": true}, "traffic_light_1": {"coords": [592, 246, 601, 265], "state": "green", "affect": true}}, "385": {"traffic_light_0": {"coords": [593, 246, 601, 265], "state": "green", "affect": true}}, "386": {"traffic_light_0": {"coords": [1120, 233, 1130, 252], "state": "green", "affect": true}, "traffic_light_1": {"coords": [594, 244, 602, 263], "state": "green", "affect": true}, "traffic_light_2": {"coords": [1210, 228, 1225, 260], "state": "green", "affect": true}}, "387": {}, "388": {"traffic_light_0": {"coords": [594, 243, 602, 262], "state": "green", "affect": true}}, "389": {"traffic_light_0": {"coords": [596, 237, 605, 258], "state": "green", "affect": true}}, "390": {"traffic_light_0": {"coords": [596, 237, 605, 257], "state": "green", "affect": true}}, "391": {"traffic_light_0": {"coords": [596, 236, 606, 256], "state": "green", "affect": true}}, "392": {"traffic_light_0": {"coords": [597, 236, 606, 256], "state": "green", "affect": true}}, "393": {"traffic_light_0": {"coords": [597, 237, 606, 256], "state": "green", "affect": true}}, "394": {"traffic_light_0": {"coords": [597, 237, 605, 256], "state": "green", "affect": true}}, "395": {"traffic_light_0": {"coords": [598, 235, 607, 254], "state": "green", "affect": true}}, "396": {"traffic_light_0": {"coords": [598, 233, 607, 254], "state": "green", "affect": true}}, "397": {"traffic_light_0": {"coords": [599, 235, 607, 255], "state": "green", "affect": true}}, "398": {"traffic_light_0": {"coords": [599, 233, 607, 254], "state": "green", "affect": true}}, "399": {"traffic_light_0": {"coords": [598, 229, 607, 251], "state": "green", "affect": true}}, "400": {"traffic_light_0": {"coords": [598, 228, 607, 250], "state": "green", "affect": true}}, "401": {"traffic_light_0": {"coords": [598, 230, 607, 252], "state": "green", "affect": true}}, "402": {"traffic_light_0": {"coords": [598, 230, 608, 252], "state": "green", "affect": true}}, "403": {"traffic_light_0": {"coords": [599, 227, 608, 250], "state": "green", "affect": true}, "traffic_light_1": {"coords": [760, 236, 772, 257], "state": "yellow", "affect": true}}, "404": {"traffic_light_0": {"coords": [762, 228, 774, 258], "state": "green", "affect": true}, "traffic_light_1": {"coords": [599, 226, 608, 249], "state": "green", "affect": true}}, "405": {"traffic_light_0": {"coords": [599, 226, 609, 249], "state": "green", "affect": true}}, "406": {"traffic_light_0": {"coords": [600, 226, 609, 248], "state": "green", "affect": true}}, "407": {"traffic_light_0": {"coords": [599, 225, 609, 248], "state": "green", "affect": true}}, "408": {"traffic_light_0": {"coords": [601, 224, 610, 246], "state": "green", "affect": true}, "traffic_light_1": {"coords": [770, 224, 784, 258], "state": "green", "affect": true}}, "409": {"traffic_light_0": {"coords": [771, 221, 785, 254], "state": "green", "affect": true}, "traffic_light_1": {"coords": [601, 223, 611, 246], "state": "green", "affect": true}}, "410": {"traffic_light_0": {"coords": [773, 222, 785, 252], "state": "green", "affect": true}, "traffic_light_1": {"coords": [600, 220, 611, 245], "state": "green", "affect": true}}, "411": {"traffic_light_0": {"coords": [775, 223, 787, 252], "state": "green", "affect": true}, "traffic_light_1": {"coords": [601, 220, 611, 243], "state": "green", "affect": true}}, "412": {"traffic_light_0": {"coords": [600, 220, 611, 243], "state": "green", "affect": true}, "traffic_light_1": {"coords": [778, 223, 788, 247], "state": "green", "affect": true}}, "413": {"traffic_light_0": {"coords": [600, 219, 611, 242], "state": "green", "affect": true}, "traffic_light_1": {"coords": [781, 221, 792, 249], "state": "green", "affect": true}}, "414": {"traffic_light_0": {"coords": [599, 218, 610, 244], "state": "green", "affect": true}, "traffic_light_1": {"coords": [781, 224, 793, 250], "state": "green", "affect": true}}, "415": {"traffic_light_0": {"coords": [599, 217, 610, 244], "state": "green", "affect": true}}, "416": {"traffic_light_0": {"coords": [598, 217, 609, 244], "state": "green", "affect": true}, "traffic_light_1": {"coords": [788, 226, 798, 249], "state": "green", "affect": true}}, "417": {"traffic_light_0": {"coords": [598, 216, 610, 243], "state": "green", "affect": true}, "traffic_light_1": {"coords": [789, 224, 799, 247], "state": "green", "affect": true}}, "418": {"traffic_light_0": {"coords": [598, 215, 609, 243], "state": "green", "affect": true}, "traffic_light_1": {"coords": [789, 222, 800, 247], "state": "green", "affect": true}}, "419": {"traffic_light_0": {"coords": [597, 211, 609, 238], "state": "green", "affect": true}, "traffic_light_1": {"coords": [793, 219, 805, 245], "state": "green", "affect": true}}, "420": {"traffic_light_0": {"coords": [597, 209, 609, 237], "state": "green", "affect": true}, "traffic_light_1": {"coords": [795, 217, 807, 243], "state": "green", "affect": true}}, "421": {"traffic_light_0": {"coords": [597, 209, 609, 236], "state": "green", "affect": true}, "traffic_light_1": {"coords": [799, 214, 811, 242], "state": "green", "affect": true}}, "422": {"traffic_light_0": {"coords": [803, 211, 815, 240], "state": "green", "affect": true}, "traffic_light_1": {"coords": [597, 204, 609, 231], "state": "green", "affect": true}}, "423": {"traffic_light_0": {"coords": [804, 208, 817, 239], "state": "green", "affect": true}}, "424": {"traffic_light_0": {"coords": [806, 209, 817, 238], "state": "green", "affect": true}, "traffic_light_1": {"coords": [597, 197, 610, 226], "state": "green", "affect": true}}, "425": {"traffic_light_0": {"coords": [811, 207, 821, 235], "state": "green", "affect": true}, "traffic_light_1": {"coords": [597, 196, 610, 224], "state": "green", "affect": true}}, "426": {"traffic_light_0": {"coords": [597, 196, 609, 224], "state": "green", "affect": true}, "traffic_light_1": {"coords": [811, 206, 824, 236], "state": "green", "affect": true}}, "427": {"traffic_light_0": {"coords": [596, 194, 609, 224], "state": "green", "affect": true}}, "428": {"traffic_light_0": {"coords": [597, 193, 609, 224], "state": "green", "affect": true}, "traffic_light_1": {"coords": [818, 202, 831, 231], "state": "green", "affect": true}}, "429": {"traffic_light_0": {"coords": [597, 192, 609, 222], "state": "green", "affect": true}}, "430": {"traffic_light_0": {"coords": [596, 189, 608, 218], "state": "green", "affect": true}, "traffic_light_1": {"coords": [824, 196, 837, 227], "state": "green", "affect": true}}, "431": {"traffic_light_0": {"coords": [597, 189, 608, 217], "state": "green", "affect": true}}, "432": {"traffic_light_0": {"coords": [596, 188, 608, 215], "state": "green", "affect": true}, "traffic_light_1": {"coords": [832, 190, 847, 223], "state": "green", "affect": true}}, "433": {"traffic_light_0": {"coords": [596, 186, 608, 213], "state": "green", "affect": true}}, "434": {"traffic_light_0": {"coords": [596, 182, 611, 215], "state": "green", "affect": true}, "traffic_light_1": {"coords": [595, 182, 606, 208], "state": "green", "affect": true}}, "435": {"traffic_light_0": {"coords": [595, 178, 609, 209], "state": "green", "affect": true}}, "436": {"traffic_light_0": {"coords": [595, 177, 611, 210], "state": "green", "affect": true}, "traffic_light_1": {"coords": [849, 173, 868, 216], "state": "green", "affect": true}}, "437": {"traffic_light_0": {"coords": [854, 177, 870, 213], "state": "green", "affect": true}, "traffic_light_1": {"coords": [595, 176, 608, 206], "state": "green", "affect": true}}, "438": {"traffic_light_0": {"coords": [596, 172, 608, 201], "state": "green", "affect": true}}, "439": {"traffic_light_0": {"coords": [595, 163, 611, 197], "state": "green", "affect": true}, "traffic_light_1": {"coords": [865, 173, 880, 207], "state": "green", "affect": true}}, "440": {"traffic_light_0": {"coords": [594, 157, 608, 193], "state": "green", "affect": true}, "traffic_light_1": {"coords": [872, 162, 889, 198], "state": "green", "affect": true}}, "441": {"traffic_light_0": {"coords": [594, 157, 607, 191], "state": "green", "affect": true}, "traffic_light_1": {"coords": [877, 157, 894, 196], "state": "green", "affect": true}}, "442": {"traffic_light_0": {"coords": [595, 155, 610, 188], "state": "green", "affect": true}, "traffic_light_1": {"coords": [883, 158, 900, 192], "state": "green", "affect": true}}, "443": {"traffic_light_0": {"coords": [595, 150, 613, 187], "state": "green", "affect": true}, "traffic_light_1": {"coords": [888, 158, 905, 190], "state": "green", "affect": true}}, "444": {"traffic_light_0": {"coords": [594, 144, 612, 183], "state": "green", "affect": true}, "traffic_light_1": {"coords": [900, 154, 915, 184], "state": "green", "affect": true}}, "445": {"traffic_light_0": {"coords": [594, 143, 611, 179], "state": "green", "affect": true}, "traffic_light_1": {"coords": [900, 135, 921, 183], "state": "green", "affect": true}}, "446": {"traffic_light_0": {"coords": [595, 139, 610, 173], "state": "green", "affect": true}, "traffic_light_1": {"coords": [908, 127, 929, 175], "state": "green", "affect": true}}, "447": {"traffic_light_0": {"coords": [594, 125, 609, 167], "state": "green", "affect": true}, "traffic_light_1": {"coords": [918, 129, 939, 167], "state": "green", "affect": true}}, "448": {"traffic_light_0": {"coords": [595, 126, 610, 163], "state": "green", "affect": true}, "traffic_light_1": {"coords": [928, 124, 944, 164], "state": "green", "affect": true}}, "449": {"traffic_light_0": {"coords": [596, 123, 612, 158], "state": "green", "affect": true}}, "450": {"traffic_light_0": {"coords": [596, 121, 610, 152], "state": "green", "affect": true}}, "451": {"traffic_light_0": {"coords": [596, 114, 610, 147], "state": "green", "affect": true}}, "452": {"traffic_light_0": {"coords": [595, 106, 610, 142], "state": "green", "affect": true}}, "453": {"traffic_light_0": {"coords": [595, 101, 609, 137], "state": "green", "affect": true}}, "454": {"traffic_light_0": {"coords": [594, 94, 610, 135], "state": "green", "affect": true}, "traffic_light_1": {"coords": [984, 86, 1004, 131], "state": "green", "affect": true}}, "455": {"traffic_light_0": {"coords": [593, 91, 611, 133], "state": "green", "affect": true}, "traffic_light_1": {"coords": [998, 80, 1017, 126], "state": "green", "affect": true}}, "456": {"traffic_light_0": {"coords": [594, 92, 612, 133], "state": "green", "affect": true}, "traffic_light_1": {"coords": [1005, 69, 1029, 126], "state": "green", "affect": true}}, "457": {"traffic_light_0": {"coords": [1019, 58, 1046, 120], "state": "green", "affect": true}, "traffic_light_1": {"coords": [595, 88, 611, 127], "state": "green", "affect": true}}, "458": {"traffic_light_0": {"coords": [1034, 53, 1062, 117], "state": "green", "affect": true}, "traffic_light_1": {"coords": [596, 83, 616, 124], "state": "green", "affect": true}}, "459": {"traffic_light_0": {"coords": [1047, 42, 1079, 114], "state": "green", "affect": true}, "traffic_light_1": {"coords": [598, 77, 618, 120], "state": "green", "affect": true}}, "460": {"traffic_light_0": {"coords": [1065, 31, 1095, 108], "state": "green", "affect": true}, "traffic_light_1": {"coords": [598, 66, 620, 113], "state": "green", "affect": true}}, "461": {"traffic_light_0": {"coords": [597, 56, 620, 105], "state": "green", "affect": true}}, "462": {"traffic_light_0": {"coords": [599, 54, 620, 99], "state": "green", "affect": true}, "traffic_light_1": {"coords": [1101, 11, 1137, 86], "state": "green", "affect": true}}, "463": {"traffic_light_0": {"coords": [597, 29, 625, 92], "state": "green", "affect": true}}, "464": {"traffic_light_0": {"coords": [598, 24, 623, 82], "state": "green", "affect": true}}, "465": {"traffic_light_0": {"coords": [599, 19, 622, 73], "state": "green", "affect": true}}, "466": {"traffic_light_0": {"coords": [599, 9, 624, 65], "state": "green", "affect": true}}, "467": {"traffic_light_0": {"coords": [598, 0, 633, 53], "state": "green", "affect": true}}, "468": {}, "469": {"traffic_light_0": {"coords": [597, 0, 638, 35], "state": "green", "affect": true}}, "470": {}, "471": {}, "472": {}, "473": {}, "474": {}, "475": {}, "476": {}, "477": {}, "478": {}, "479": {}, "480": {}, "481": {}, "482": {}, "483": {}, "484": {"traffic_light_0": {"coords": [476, 268, 484, 282], "state": "red", "affect": true}}, "485": {"traffic_light_0": {"coords": [476, 266, 484, 283], "state": "red", "affect": true}}, "486": {"traffic_light_0": {"coords": [475, 267, 484, 283], "state": "red", "affect": true}}, "487": {"traffic_light_0": {"coords": [476, 266, 485, 282], "state": "red", "affect": true}}, "488": {"traffic_light_0": {"coords": [475, 265, 484, 282], "state": "red", "affect": true}}, "489": {}, "490": {}, "491": {}, "492": {}, "493": {}, "494": {"traffic_light_0": {"coords": [469, 269, 478, 285], "state": "red", "affect": true}}, "495": {"traffic_light_0": {"coords": [469, 268, 477, 283], "state": "red", "affect": true}}, "496": {"traffic_light_0": {"coords": [469, 267, 477, 282], "state": "red", "affect": true}}, "497": {"traffic_light_0": {"coords": [468, 268, 476, 283], "state": "red", "affect": true}}, "498": {"traffic_light_0": {"coords": [467, 268, 476, 283], "state": "red", "affect": true}}, "499": {"traffic_light_0": {"coords": [464, 268, 473, 286], "state": "red", "affect": true}}, "500": {"traffic_light_0": {"coords": [462, 268, 472, 286], "state": "red", "affect": true}}, "501": {"traffic_light_0": {"coords": [464, 268, 473, 285], "state": "red", "affect": true}}, "502": {"traffic_light_0": {"coords": [461, 268, 469, 283], "state": "red", "affect": true}}, "503": {"traffic_light_0": {"coords": [461, 268, 469, 283], "state": "red", "affect": true}}, "504": {"traffic_light_0": {"coords": [461, 268, 469, 283], "state": "red", "affect": true}}, "505": {"traffic_light_0": {"coords": [459, 266, 468, 284], "state": "red", "affect": true}}, "506": {"traffic_light_0": {"coords": [460, 266, 467, 283], "state": "red", "affect": true}}, "507": {}, "508": {"traffic_light_0": {"coords": [454, 263, 463, 282], "state": "red", "affect": true}}, "509": {"traffic_light_0": {"coords": [452, 263, 461, 281], "state": "red", "affect": true}}, "510": {"traffic_light_0": {"coords": [453, 264, 461, 282], "state": "red", "affect": true}}, "511": {"traffic_light_0": {"coords": [453, 263, 461, 281], "state": "red", "affect": true}}, "512": {"traffic_light_0": {"coords": [452, 262, 460, 280], "state": "red", "affect": true}}, "513": {"traffic_light_0": {"coords": [448, 262, 456, 279], "state": "red", "affect": true}}, "514": {"traffic_light_0": {"coords": [445, 264, 453, 282], "state": "red", "affect": true}}, "515": {"traffic_light_0": {"coords": [445, 264, 453, 283], "state": "red", "affect": true}}, "516": {"traffic_light_0": {"coords": [444, 262, 452, 278], "state": "red", "affect": true}}, "517": {"traffic_light_0": {"coords": [440, 261, 448, 279], "state": "red", "affect": true}}, "518": {"traffic_light_0": {"coords": [438, 262, 446, 279], "state": "red", "affect": true}}, "519": {"traffic_light_0": {"coords": [439, 260, 447, 278], "state": "red", "affect": true}}, "520": {}, "521": {"traffic_light_0": {"coords": [429, 263, 437, 283], "state": "red", "affect": true}}, "522": {"traffic_light_0": {"coords": [426, 262, 435, 284], "state": "red", "affect": true}}, "523": {"traffic_light_0": {"coords": [422, 263, 431, 283], "state": "red", "affect": true}}, "524": {"traffic_light_0": {"coords": [422, 260, 430, 279], "state": "red", "affect": true}, "traffic_light_1": {"coords": [627, 265, 634, 282], "state": "green", "affect": true}}, "525": {}, "526": {}, "527": {}, "528": {}, "529": {"traffic_light_0": {"coords": [407, 257, 416, 275], "state": "red", "affect": true}}, "530": {"traffic_light_0": {"coords": [403, 253, 413, 274], "state": "red", "affect": true}}, "531": {"traffic_light_0": {"coords": [400, 253, 411, 274], "state": "red", "affect": true}, "traffic_light_1": {"coords": [398, 253, 407, 273], "state": "red", "affect": true}}, "532": {"traffic_light_0": {"coords": [397, 253, 406, 276], "state": "red", "affect": true}}, "533": {"traffic_light_0": {"coords": [392, 253, 400, 273], "state": "red", "affect": true}, "traffic_light_1": {"coords": [450, 233, 459, 253], "state": "red", "affect": true}}, "534": {"traffic_light_0": {"coords": [391, 252, 400, 270], "state": "red", "affect": true}}, "535": {}, "536": {}, "537": {}, "538": {}, "539": {}, "540": {"traffic_light_0": {"coords": [429, 220, 439, 243], "state": "green", "affect": true}}, "541": {}, "542": {}, "543": {}, "544": {}, "545": {"traffic_light_0": {"coords": [352, 240, 361, 259], "state": "red", "affect": true}}, "546": {"traffic_light_0": {"coords": [407, 219, 418, 242], "state": "red", "affect": true}, "traffic_light_1": {"coords": [346, 241, 355, 260], "state": "red", "affect": true}}, "547": {"traffic_light_0": {"coords": [404, 218, 415, 242], "state": "red", "affect": true}, "traffic_light_1": {"coords": [344, 239, 354, 257], "state": "red", "affect": true}}, "548": {"traffic_light_0": {"coords": [403, 218, 414, 241], "state": "red", "affect": true}}, "549": {}, "550": {"traffic_light_0": {"coords": [336, 235, 346, 253], "state": "red", "affect": true}}, "551": {"traffic_light_0": {"coords": [329, 236, 337, 251], "state": "red", "affect": true}}, "552": {"traffic_light_0": {"coords": [329, 235, 337, 250], "state": "red", "affect": true}}, "553": {"traffic_light_0": {"coords": [327, 233, 335, 249], "state": "red", "affect": true}}, "554": {"traffic_light_0": {"coords": [324, 232, 332, 248], "state": "red", "affect": true}}, "555": {"traffic_light_0": {"coords": [321, 232, 330, 252], "state": "red", "affect": true}}, "556": {"traffic_light_0": {"coords": [582, 229, 592, 251], "state": "green", "affect": true}, "traffic_light_1": {"coords": [318, 230, 327, 250], "state": "red", "affect": true}}, "557": {"traffic_light_0": {"coords": [315, 233, 322, 247], "state": "red", "affect": true}, "traffic_light_1": {"coords": [582, 229, 592, 250], "state": "green", "affect": true}, "traffic_light_2": {"coords": [375, 203, 386, 226], "state": "red", "affect": true}}, "558": {"traffic_light_0": {"coords": [374, 202, 385, 225], "state": "red", "affect": true}, "traffic_light_1": {"coords": [315, 231, 322, 246], "state": "red", "affect": true}}, "559": {}, "560": {}, "561": {}, "562": {}, "563": {}, "564": {}, "565": {"traffic_light_0": {"coords": [295, 221, 305, 241], "state": "red", "affect": true}}, "566": {"traffic_light_0": {"coords": [292, 220, 302, 243], "state": "red", "affect": true}}, "567": {"traffic_light_0": {"coords": [292, 220, 303, 245], "state": "red", "affect": true}}, "568": {}, "569": {"traffic_light_0": {"coords": [284, 221, 294, 241], "state": "red", "affect": true}}, "570": {"traffic_light_0": {"coords": [283, 220, 292, 240], "state": "red", "affect": true}}, "571": {"traffic_light_0": {"coords": [282, 221, 292, 241], "state": "red", "affect": true}}, "572": {}, "573": {}, "574": {}, "575": {}, "576": {}, "577": {}, "578": {}, "579": {}, "580": {}, "581": {}, "582": {}, "583": {}, "584": {"traffic_light_0": {"coords": [604, 191, 615, 220], "state": "red", "affect": true}}, "585": {"traffic_light_0": {"coords": [606, 190, 617, 217], "state": "red", "affect": true}}, "586": {"traffic_light_0": {"coords": [606, 189, 617, 214], "state": "red", "affect": true}}, "587": {"traffic_light_0": {"coords": [607, 189, 617, 214], "state": "red", "affect": true}}, "588": {"traffic_light_0": {"coords": [607, 190, 618, 217], "state": "red", "affect": true}, "traffic_light_1": {"coords": [288, 131, 303, 167], "state": "red", "affect": true}}, "589": {"traffic_light_0": {"coords": [609, 189, 620, 218], "state": "red", "affect": true}}, "590": {"traffic_light_0": {"coords": [611, 189, 623, 215], "state": "red", "affect": true}}, "591": {"traffic_light_0": {"coords": [612, 187, 624, 214], "state": "red", "affect": true}}, "592": {"traffic_light_0": {"coords": [614, 187, 626, 214], "state": "red", "affect": true}}, "593": {"traffic_light_0": {"coords": [277, 123, 292, 161], "state": "red", "affect": true}}, "594": {"traffic_light_0": {"coords": [273, 119, 290, 161], "state": "red", "affect": true}}, "595": {"traffic_light_0": {"coords": [271, 118, 293, 160], "state": "red", "affect": true}}, "596": {"traffic_light_0": {"coords": [269, 113, 288, 160], "state": "red", "affect": true}}, "597": {}, "598": {"traffic_light_0": {"coords": [626, 173, 639, 203], "state": "red", "affect": true}, "traffic_light_1": {"coords": [262, 106, 280, 146], "state": "red", "affect": true}}, "599": {"traffic_light_0": {"coords": [627, 172, 640, 202], "state": "red", "affect": true}}, "600": {"traffic_light_0": {"coords": [628, 171, 642, 201], "state": "red", "affect": true}, "traffic_light_1": {"coords": [258, 102, 273, 134], "state": "red", "affect": true}}, "601": {}, "602": {"traffic_light_0": {"coords": [634, 169, 647, 200], "state": "red", "affect": true}}, "603": {"traffic_light_0": {"coords": [636, 169, 648, 199], "state": "red", "affect": true}}, "604": {}, "605": {}, "606": {}, "607": {}, "608": {}, "609": {}, "610": {}, "611": {}, "612": {}, "613": {}, "614": {}, "615": {}, "616": {}, "617": {}, "618": {}, "619": {}, "620": {}, "621": {}, "622": {}, "623": {}, "624": {}, "625": {}, "626": {}, "627": {}, "628": {}, "629": {}, "630": {}, "631": {}, "632": {}, "633": {}, "634": {}, "635": {}, "636": {}, "637": {}, "638": {}, "639": {}, "640": {}, "641": {}, "642": {}, "643": {}, "644": {}, "645": {}, "646": {}, "647": {}, "648": {}, "649": {}, "650": {}, "651": {}, "652": {}, "653": {}, "654": {}, "655": {}, "656": {}, "657": {}, "658": {}, "659": {}, "660": {}, "661": {}, "662": {}, "663": {}, "664": {}, "665": {}, "666": {}, "667": {}, "668": {}, "669": {}, "670": {}, "671": {}, "672": {}, "673": {}, "674": {}, "675": {}, "676": {}, "677": {}, "678": {}, "679": {}, "680": {}, "681": {}, "682": {}, "683": {}, "684": {}, "685": {}, "686": {}, "687": {}, "688": {}, "689": {}, "690": {}, "691": {}, "692": {}, "693": {}, "694": {}, "695": {}, "696": {}, "697": {}, "698": {}, "699": {}, "700": {}, "701": {}, "702": {}, "703": {}, "704": {}, "705": {}, "706": {}, "707": {}, "708": {}, "709": {}, "710": {}, "711": {}, "712": {}, "713": {}, "714": {}, "715": {}, "716": {}, "717": {}, "718": {}, "719": {}, "720": {}, "721": {}, "722": {}, "723": {}, "724": {}, "725": {}, "726": {}, "727": {}, "728": {}, "729": {}, "730": {}, "731": {}, "732": {}, "733": {}, "734": {}, "735": {}, "736": {}, "737": {}, "738": {}, "739": {}, "740": {}, "741": {}, "742": {}, "743": {}, "744": {}, "745": {}, "746": {}, "747": {}, "748": {}, "749": {}, "750": {}, "751": {}, "752": {}, "753": {}, "754": {}, "755": {}, "756": {}, "757": {}, "758": {}, "759": {}, "760": {}, "761": {}, "762": {}, "763": {}, "764": {}, "765": {}, "766": {}, "767": {}, "768": {}, "769": {}, "770": {}, "771": {}, "772": {}, "773": {}, "774": {}, "775": {}, "776": {}, "777": {}, "778": {}, "779": {}, "780": {}, "781": {}, "782": {}, "783": {}, "784": {}, "785": {}, "786": {}, "787": {}, "788": {}, "789": {}, "790": {}, "791": {}, "792": {}, "793": {}, "794": {}, "795": {}, "796": {}, "797": {}, "798": {}, "799": {}, "800": {}, "801": {}, "802": {}, "803": {}, "804": {}, "805": {}, "806": {}, "807": {}, "808": {}, "809": {}, "810": {}, "811": {}, "812": {}, "813": {}, "814": {}, "815": {}, "816": {}, "817": {}, "818": {}, "819": {}, "820": {}, "821": {}, "822": {}, "823": {}, "824": {}, "825": {}, "826": {}, "827": {}, "828": {}, "829": {}, "830": {}, "831": {}, "832": {}, "833": {}, "834": {}, "835": {}, "836": {}, "837": {}, "838": {}, "839": {}, "840": {}, "841": {}, "842": {}, "843": {}, "844": {}, "845": {}, "846": {}, "847": {}, "848": {}, "849": {}, "850": {}, "851": {}, "852": {}, "853": {}, "854": {}, "855": {}, "856": {}, "857": {}, "858": {}, "859": {}, "860": {}, "861": {}, "862": {}, "863": {}, "864": {}, "865": {}, "866": {}, "867": {}, "868": {}, "869": {}, "870": {}, "871": {}, "872": {}, "873": {}, "874": {}, "875": {}, "876": {}, "877": {}, "878": {}, "879": {}, "880": {}, "881": {}, "882": {}, "883": {}, "884": {}, "885": {}, "886": {}, "887": {}, "888": {}, "889": {}, "890": {}, "891": {}, "892": {}, "893": {}, "894": {}, "895": {}, "896": {}, "897": {}, "898": {}, "899": {}, "900": {}, "901": {}, "902": {}, "903": {}, "904": {}, "905": {}, "906": {}, "907": {}, "908": {}, "909": {}, "910": {}, "911": {}, "912": {}, "913": {}, "914": {}, "915": {}, "916": {}, "917": {}, "918": {}, "919": {}, "920": {}, "921": {}, "922": {}, "923": {}, "924": {}, "925": {}, "926": {}, "927": {}, "928": {}, "929": {}, "930": {}, "931": {}, "932": {}, "933": {}, "934": {}, "935": {}, "936": {}, "937": {}, "938": {}, "939": {}, "940": {}, "941": {}, "942": {}, "943": {}, "944": {}, "945": {}, "946": {}, "947": {}, "948": {}, "949": {}, "950": {}, "951": {}, "952": {}, "953": {}, "954": {}, "955": {}, "956": {}, "957": {}, "958": {}, "959": {}, "960": {}, "961": {}, "962": {}, "963": {}, "964": {}, "965": {}, "966": {}, "967": {}, "968": {}, "969": {}, "970": {}, "971": {}, "972": {}, "973": {}, "974": {}, "975": {}, "976": {}, "977": {}, "978": {}, "979": {}, "980": {}, "981": {}, "982": {}, "983": {}, "984": {}, "985": {}, "986": {}, "987": {}, "988": {}, "989": {}, "990": {}, "991": {}, "992": {}, "993": {}, "994": {}, "995": {}, "996": {}, "997": {}, "998": {}, "999": {}, "1000": {}, "1001": {}, "1002": {}, "1003": {}, "1004": {}, "1005": {}, "1006": {}, "1007": {}, "1008": {}, "1009": {}, "1010": {}, "1011": {}, "1012": {}, "1013": {}, "1014": {}, "1015": {}, "1016": {}, "1017": {}, "1018": {}, "1019": {}, "1020": {}, "1021": {}, "1022": {}, "1023": {}, "1024": {}, "1025": {}, "1026": {}, "1027": {}, "1028": {}, "1029": {}, "1030": {}, "1031": {}, "1032": {}, "1033": {}, "1034": {}, "1035": {}, "1036": {}, "1037": {}, "1038": {}, "1039": {}, "1040": {}, "1041": {}, "1042": {}, "1043": {}, "1044": {}, "1045": {}, "1046": {}, "1047": {}, "1048": {}, "1049": {}, "1050": {}, "1051": {}, "1052": {}, "1053": {}, "1054": {}, "1055": {}, "1056": {}, "1057": {}, "1058": {}, "1059": {}, "1060": {}, "1061": {}, "1062": {}, "1063": {}, "1064": {}, "1065": {}, "1066": {}, "1067": {}, "1068": {}, "1069": {}, "1070": {}, "1071": {}, "1072": {}, "1073": {}, "1074": {}, "1075": {}, "1076": {}, "1077": {}, "1078": {}, "1079": {}, "1080": {}, "1081": {}, "1082": {}, "1083": {}, "1084": {}, "1085": {}, "1086": {}, "1087": {}, "1088": {}, "1089": {}, "1090": {}, "1091": {}, "1092": {}, "1093": {}, "1094": {}, "1095": {}, "1096": {}, "1097": {}, "1098": {}, "1099": {}, "1100": {}, "1101": {}, "1102": {}, "1103": {}, "1104": {}, "1105": {}, "1106": {}, "1107": {}, "1108": {}, "1109": {}, "1110": {}, "1111": {}, "1112": {}, "1113": {}, "1114": {}, "1115": {}, "1116": {}, "1117": {}, "1118": {}, "1119": {}, "1120": {}, "1121": {}, "1122": {}, "1123": {}, "1124": {}, "1125": {}, "1126": {}, "1127": {}, "1128": {}, "1129": {}, "1130": {}, "1131": {}, "1132": {}, "1133": {}, "1134": {}, "1135": {}, "1136": {}, "1137": {}, "1138": {}, "1139": {}, "1140": {}, "1141": {}, "1142": {}, "1143": {}, "1144": {}, "1145": {}, "1146": {}, "1147": {}, "1148": {}, "1149": {}, "1150": {}, "1151": {}, "1152": {}, "1153": {}, "1154": {}, "1155": {}, "1156": {}, "1157": {}, "1158": {}, "1159": {}, "1160": {}, "1161": {}, "1162": {}, "1163": {}, "1164": {}, "1165": {}, "1166": {}, "1167": {}, "1168": {}, "1169": {}, "1170": {}, "1171": {}, "1172": {}, "1173": {}, "1174": {}, "1175": {}, "1176": {}, "1177": {}, "1178": {}, "1179": {}, "1180": {}, "1181": {}, "1182": {}, "1183": {}, "1184": {}, "1185": {}, "1186": {}, "1187": {}, "1188": {}, "1189": {}, "1190": {}, "1191": {}, "1192": {}, "1193": {}, "1194": {}, "1195": {}, "1196": {}, "1197": {}, "1198": {}, "1199": {}, "1200": {}, "1201": {}, "1202": {}}